agentmatrix/MultiAgentSystem.py
agentmatrix/__init__.py
agentmatrix/agents/__init__.py
agentmatrix/agents/base_agent.py
agentmatrix/agents/duckduckgo_agent.py
agentmatrix/agents/llm_agent.py
agentmatrix/utils/__init__.py
agentmatrix/utils/helpers.py
agentmatrix-0.1.0.dist-info/METADATA
agentmatrix-0.1.0.dist-info/WHEEL
agentmatrix-0.1.0.dist-info/top_level.txt
agentmatrix-0.1.0.dist-info/RECORD
