Metadata-Version: 2.1
Name: agentmatrix
Version: 0.1.0
Summary: A multi-agent system for processing queries using DuckDuckGo and LLM agents
Home-page: https://github.com/kiranbeethoju/agentmatrix
Author: Kiran Beethoju
Author-email: kiranbeethoju@gmail.com
Classifier: Development Status :: 3 - Alpha
Classifier: Intended Audience :: Developers
Classifier: License :: OSI Approved :: MIT License
Classifier: Operating System :: OS Independent
Classifier: Programming Language :: Python :: 3
Classifier: Programming Language :: Python :: 3.7
Classifier: Programming Language :: Python :: 3.8
Classifier: Programming Language :: Python :: 3.9
Classifier: Programming Language :: Python :: 3.10
Requires-Python: >=3.7
Requires-Dist: requests
Requires-Dist: openai
